Metadata-Version: 2.1
Name: fillme
Version: 1.0.0
Summary: A lightweight library to generate dummy data for database using OpenAI
Author: Soheil Dolatabadi
Author-email: Soheil Dolatabadi <soheildolat@gmail.com>
License: MIT License
Project-URL: Homepage, https://github.com/soheil-star01/fillme
Keywords: dummy data,openai,chatgpt,database,postgresql
Classifier: License :: OSI Approved :: MIT License
Classifier: Programming Language :: Python
Classifier: Programming Language :: Python :: 3
Requires-Python: >=3.10
License-File: LICENSE
Requires-Dist: openai==1.12.0
Requires-Dist: sqlalchemy==2.0.27
Provides-Extra: dev
Requires-Dist: black; extra == "dev"
Requires-Dist: bumpver; extra == "dev"
Requires-Dist: isort; extra == "dev"
Requires-Dist: pip-tools; extra == "dev"
Requires-Dist: pytest; extra == "dev"
